cpppm/__init__.py
cpppm/cli.py
cpppm/conans.py
cpppm/config.py
cpppm/events.py
cpppm/executable.py
cpppm/library.py
cpppm/project.py
cpppm/target.py
cpppm/build/__init__.py
cpppm/build/compiler.py
cpppm/cache/__init__.py
cpppm/detect/__init__.py
cpppm/detect/compiles.py
cpppm/templates/__init__.py
cpppm/templates/conanfilev2.py.j2
cpppm/toolchains/__init__.py
cpppm/toolchains/msvc.py
cpppm/toolchains/toolchain.py
cpppm/utils/__init__.py
cpppm/utils/decorators.py
cpppm/utils/pathlist.py
cpppm/utils/runner.py
cpppm/utils/sha.py
cpppm/utils/types.py
unittests/__init__.py
unittests/project.py
unittests/utils/__init__.py
unittests/utils/pathlist.py
unittests/utils/decorators/__init__.py
unittests/utils/decorators/collectable.py
unittests/utils/decorators/list_property.py
cpppm-1.0.0.dist-info/LICENSE
cpppm-1.0.0.dist-info/METADATA
cpppm-1.0.0.dist-info/WHEEL
cpppm-1.0.0.dist-info/top_level.txt
cpppm-1.0.0.dist-info/RECORD
