Metadata-Version: 2.1
Name: cpppm
Version: 1.0.0
Summary: CPP Package Manager
Home-page: https://github.com/Garcia6l20/cpppm
Author: Garcia Sylvain
Author-email: garcia.6l20@gmail.com
License: MIT
Keywords: c++,project-manager,cmake,conan
Platform: UNKNOWN
Classifier: Development Status :: 3 - Alpha
Classifier: Intended Audience :: Developers
Classifier: Topic :: Software Development :: Build Tools
Classifier: License :: OSI Approved :: MIT License
Classifier: Operating System :: OS Independent
Classifier: Programming Language :: Python :: 3.8
Requires-Python: >=3.8
Requires-Dist: Click (>=7.1.2)
Requires-Dist: conan (>=1.31.2)
Requires-Dist: jinja2 (>=2.11.2)
Requires-Dist: nest-asyncio (>=1.4.3)
Requires-Dist: semantic-version (>=2.8.5)
Provides-Extra: interactive
Requires-Dist: IPython (>=7.19) ; extra == 'interactive'
Provides-Extra: shell
Requires-Dist: click-shell (>=2.0) ; extra == 'shell'
